hookdns/__init__.py
hookdns/getaddrinfo.py
hookdns/gethostbyname.py
hookdns/gethostbyname_ex.py
hookdns/hosts.py
hookdns-2.0.0.dist-info/LICENSE
hookdns-2.0.0.dist-info/METADATA
hookdns-2.0.0.dist-info/WHEEL
hookdns-2.0.0.dist-info/top_level.txt
hookdns-2.0.0.dist-info/RECORD
