Metadata-Version: 2.2
Name: hookdns
Version: 2.0.0
Summary: An easy way to customize the dns resolution
Author-email: cle-b <cle@tictac.pm>
License: Apache-2.0
Project-URL: repository, https://github.com/cle-b/hookdns
Classifier: Programming Language :: Python :: 3
Classifier: License :: OSI Approved :: Apache Software License
Classifier: Operating System :: OS Independent
Classifier: Development Status :: 5 - Production/Stable
Classifier: Topic :: Internet :: Name Service (DNS)
Requires-Python: >=3.8
License-File: LICENSE
